neinsum/__about__.py
neinsum/__init__.py
neinsum/_named_einsum.py
neinsum-1.0.2.dist-info/LICENSE
neinsum-1.0.2.dist-info/METADATA
neinsum-1.0.2.dist-info/WHEEL
neinsum-1.0.2.dist-info/top_level.txt
neinsum-1.0.2.dist-info/RECORD
