Metadata-Version: 2.1
Name: neinsum
Version: 1.0.2
Summary: NumPy's Einsum, but with named subscripts.
Author: Andreas Dutzler
Author-email: a.dutzler@gmail.com
License: MIT License
Project-URL: Homepage, https://github.com/adtzlr/named-einsum
Project-URL: Code, https://github.com/adtzlr/named-einsum
Project-URL: Issues, https://github.com/adtzlr/named-einsum/issues
Keywords: python,numpy,einsum
Classifier: Development Status :: 5 - Production/Stable
Classifier: Programming Language :: Python
Classifier: Intended Audience :: Science/Research
Classifier: License :: OSI Approved :: MIT License
Classifier: Operating System :: OS Independent
Classifier: Programming Language :: Python
Classifier: Programming Language :: Python :: 3
Classifier: Programming Language :: Python :: 3.8
Classifier: Programming Language :: Python :: 3.9
Classifier: Programming Language :: Python :: 3.10
Classifier: Programming Language :: Python :: 3.11
Classifier: Programming Language :: Python :: 3.12
Classifier: Topic :: Scientific/Engineering
Classifier: Topic :: Scientific/Engineering :: Mathematics
Classifier: Topic :: Utilities
Requires-Python: >=3.8
License-File: LICENSE
Requires-Dist: numpy
